ssmenv2exec.py
ssmenv2exec-0.0.1.dist-info/LICENSE
ssmenv2exec-0.0.1.dist-info/METADATA
ssmenv2exec-0.0.1.dist-info/WHEEL
ssmenv2exec-0.0.1.dist-info/entry_points.txt
ssmenv2exec-0.0.1.dist-info/top_level.txt
ssmenv2exec-0.0.1.dist-info/RECORD
