Metadata-Version: 2.1
Name: ssmenv2exec
Version: 0.0.1
Summary: Pass AWS SSM parameters as environment variables when executing a process
Home-page: https://github.com/jowage58/ssmenv2exec/
Author: John Wagenleitner
Author-email: johnwa@mail.fresnostate.edu
License: UNKNOWN
Project-URL: Bug Reports, https://github.com/jowage58/ssmenv2exec/issues
Project-URL: Source, https://github.com/jowage58/ssmenv2exec/
Keywords: aws ssm paraemters environment
Platform: UNKNOWN
Classifier: Development Status :: 3 - Alpha
Classifier: Environment :: Console
Classifier: Intended Audience :: System Administrators
Classifier: Topic :: Software Development :: Build Tools
Classifier: License :: OSI Approved :: Apache Software License
Classifier: Programming Language :: Python :: 3
Classifier: Programming Language :: Python :: 3.6
Classifier: Programming Language :: Python :: 3.7
Classifier: Programming Language :: Python :: 3.8
Requires-Python: >=3.6, <4
Requires-Dist: boto3 (>=1.5)
